kuristo/__init__.py
kuristo/__main__.py
kuristo/_version.py
kuristo/action_factory.py
kuristo/config.py
kuristo/context.py
kuristo/env.py
kuristo/job.py
kuristo/job_spec.py
kuristo/plugin_loader.py
kuristo/registry.py
kuristo/resources.py
kuristo/scanner.py
kuristo/scheduler.py
kuristo/ui.py
kuristo/utils.py
kuristo/actions/__init__.py
kuristo/actions/action.py
kuristo/actions/checks_convergence_rate.py
kuristo/actions/checks_cvsdiff.py
kuristo/actions/checks_exodiff.py
kuristo/actions/checks_h5diff.py
kuristo/actions/checks_regex.py
kuristo/actions/checks_regex_float.py
kuristo/actions/composite_action.py
kuristo/actions/function_action.py
kuristo/actions/mpi_action.py
kuristo/actions/process_action.py
kuristo/actions/regex_base.py
kuristo/actions/shell_action.py
kuristo/batch/__init__.py
kuristo/batch/backend.py
kuristo/batch/slurm.py
kuristo/cli/__init__.py
kuristo/cli/_batch.py
kuristo/cli/_doctor.py
kuristo/cli/_list.py
kuristo/cli/_log.py
kuristo/cli/_report.py
kuristo/cli/_run.py
kuristo/cli/_show.py
kuristo/cli/_status.py
kuristo/templates/slurm_job.sh.j2
kuristo-0.9.2.dist-info/licenses/LICENSE
kuristo-0.9.2.dist-info/METADATA
kuristo-0.9.2.dist-info/WHEEL
kuristo-0.9.2.dist-info/entry_points.txt
kuristo-0.9.2.dist-info/top_level.txt
kuristo-0.9.2.dist-info/RECORD
