Metadata-Version: 2.4
Name: kuristo
Version: 0.9.2
Summary: A simple automation framework
Author-email: David Andrs <andrsd@gmail.com>
License-Expression: MIT
Requires-Python: <3.14,>=3.10
License-File: LICENSE
Requires-Dist: pyyaml
Requires-Dist: rich
Requires-Dist: networkx
Requires-Dist: jinja2
Requires-Dist: pydantic
Requires-Dist: h5py
Dynamic: license-file
